crosstabs_mcp/__init__.py
crosstabs_mcp/advanced_stats.py
crosstabs_mcp/server.py
crosstabs-1.0.2.dist-info/METADATA
crosstabs-1.0.2.dist-info/WHEEL
crosstabs-1.0.2.dist-info/entry_points.txt
crosstabs-1.0.2.dist-info/RECORD
