Metadata-Version: 2.4
Name: crosstabs
Version: 1.0.2
Summary: MCP server for statistical crosstabulation analysis with 40+ tools
Project-URL: Homepage, https://crosstabs.com
Project-URL: Repository, https://github.com/barangaroo/crosstabs-lite
Project-URL: Documentation, https://crosstabs.com
Project-URL: Issues, https://github.com/barangaroo/crosstabs-lite/issues
Author: Crosstabs Team
License-Expression: MIT
Keywords: chi-square,contingency-tables,cramers-v,crosstabs,fisher-exact,mcp,model-context-protocol,odds-ratio,statistical-analysis,statistics
Classifier: Development Status :: 4 - Beta
Classifier: Intended Audience :: Developers
Classifier: Intended Audience :: Science/Research
Classifier: License :: OSI Approved :: MIT License
Classifier: Programming Language :: Python :: 3
Classifier: Programming Language :: Python :: 3.10
Classifier: Programming Language :: Python :: 3.11
Classifier: Programming Language :: Python :: 3.12
Classifier: Programming Language :: Python :: 3.13
Classifier: Topic :: Scientific/Engineering :: Information Analysis
Classifier: Topic :: Scientific/Engineering :: Mathematics
Requires-Python: >=3.10
Requires-Dist: fastmcp>=0.1.0
Requires-Dist: mcp>=1.0.0
Requires-Dist: numpy>=1.24.0
Requires-Dist: pandas>=2.0.0
Requires-Dist: scipy>=1.10.0
Requires-Dist: statsmodels>=0.14.0
Provides-Extra: dev
Requires-Dist: pytest-cov>=4.0.0; extra == 'dev'
Requires-Dist: pytest>=7.0.0; extra == 'dev'
